setup.py
pablo/__init__.py
pablo/analysis.py
pablo/datastore.py
pablo/diglet.py
pablo/heuristics.py
pablo/mutate.py
pablo/producer.py
pablo.egg-info/PKG-INFO
pablo.egg-info/SOURCES.txt
pablo.egg-info/dependency_links.txt
pablo.egg-info/entry_points.txt
pablo.egg-info/requires.txt
pablo.egg-info/top_level.txt