Metadata-Version: 1.0
Name: pablo
Version: 0.1.0
Summary: automatic sketching of plunderphonic songs
Home-page: https://github.com/ftzeng/pablo
Author: Francis Tseng
Author-email: f@frnsys.com
License: MIT
Platform: UNKNOWN
